README.md
setup.py
acceldata/airflow/__init__.py
acceldata/airflow/constants.py
acceldata/airflow/listener.py
acceldata/airflow/plugin.py
acceldata/airflow/utils.py
adoc_airflow_plugin.egg-info/PKG-INFO
adoc_airflow_plugin.egg-info/SOURCES.txt
adoc_airflow_plugin.egg-info/dependency_links.txt
adoc_airflow_plugin.egg-info/entry_points.txt
adoc_airflow_plugin.egg-info/not-zip-safe
adoc_airflow_plugin.egg-info/requires.txt
adoc_airflow_plugin.egg-info/top_level.txt