Metadata-Version: 2.1
Name: adoc_airflow_plugin
Version: 4.0.1
Summary: Acceldata Airflow Listener Plugin
Author: acceldata
Keywords: acceldata
Requires-Python: >=3.8
Requires-Dist: acceldata-sdk>=4.8.1
